PMKL/KernelFunctions.py
PMKL/Optimization.py
PMKL/PMKL.py
PMKL/Transformation.py
PMKL/__init__.py
pyPMKL/KernelFunctions.py
pyPMKL/Optimization.py
pyPMKL/PMKL.py
pyPMKL/Transformation.py
pyPMKL/__init__.py
pyPMKL-0.1.5.dist-info/LICENSE.txt
pyPMKL-0.1.5.dist-info/METADATA
pyPMKL-0.1.5.dist-info/WHEEL
pyPMKL-0.1.5.dist-info/top_level.txt
pyPMKL-0.1.5.dist-info/RECORD
